wallin/__init__.py
wallin/solver.py
wallin-1.0.3.dist-info/licenses/LICENSE
wallin-1.0.3.dist-info/METADATA
wallin-1.0.3.dist-info/WHEEL
wallin-1.0.3.dist-info/top_level.txt
wallin-1.0.3.dist-info/RECORD
