Metadata-Version: 2.4
Name: wallin
Version: 1.0.3
Summary: Constraint-based Excel optimizer powered by OR-Tools
Author: Jake Wallin
License-Expression: MIT
Requires-Python: >=3.7
License-File: LICENSE
Requires-Dist: pandas
Requires-Dist: ortools
Dynamic: license-file
Dynamic: requires-python
